.gitignore
MANIFEST.in
README.rst
bootstrap.py
buildout.cfg
setup.py
collective/__init__.py
collective.js.galleriffic.egg-info/PKG-INFO
collective.js.galleriffic.egg-info/SOURCES.txt
collective.js.galleriffic.egg-info/dependency_links.txt
collective.js.galleriffic.egg-info/entry_points.txt
collective.js.galleriffic.egg-info/namespace_packages.txt
collective.js.galleriffic.egg-info/not-zip-safe
collective.js.galleriffic.egg-info/requires.txt
collective.js.galleriffic.egg-info/top_level.txt
collective/js/__init__.py
collective/js/galleriffic/__init__.py
collective/js/galleriffic/configure.zcml
collective/js/galleriffic/jquery.galleriffic.js
collective/js/galleriffic/jquery.opacityrollover.js
collective/js/galleriffic/profiles/default/jsregistry.xml
collective/js/galleriffic/profiles/default/metadata.xml
collective/js/galleriffic/tests/__init__.py
collective/js/galleriffic/tests/base.py
collective/js/galleriffic/tests/test_setup.py
docs/HISTORY.txt