Metadata-Version: 1.0
Name: collective.js.galleriffic
Version: 1.1
Summary: JQuery galleriffic javascript integration as browser resource
Home-page: https://github.com/collective/collective.js.galleriffic
Author: JeanMichel FRANCOIS aka toutpt
Author-email: toutpt@gmail.com
License: GPL
Keywords: plone javascript galleriffic jquery
Platform: UNKNOWN
Classifier: Environment :: Web Environment
Classifier: License :: OSI Approved :: GNU General Public License (GPL)
Classifier: Operating System :: OS Independent
Classifier: Framework :: Plone
Classifier: Framework :: Plone :: 4.0
Classifier: Framework :: Plone :: 4.1
Classifier: Programming Language :: Python
